haoqiren_py/base/datetime.cp36-win32.pyd
haoqiren_py/base/platform.cp36-win32.pyd
haoqiren_py/const/const_char.cp36-win32.pyd
haoqiren_py/cvt/cvt_base.cp36-win32.pyd
haoqiren_py/io/directory.cp36-win32.pyd
haoqiren_py/io/file.cp36-win32.pyd
haoqiren_py/io/path.cp36-win32.pyd
haoqiren_py/math/prime.cp36-win32.pyd
haoqiren_py/office/excel/openpyxl/xlrange.cp36-win32.pyd
haoqiren_py/office/excel/openpyxl/xlworkbook.cp36-win32.pyd
haoqiren_py/office/excel/openpyxl/xlworksheet.cp36-win32.pyd
haoqiren_py/office/excel/xlcvt/xlconvertor.cp36-win32.pyd
haoqiren_py/office/excel/xlrwu/xlworkbook.cp36-win32.pyd
haoqiren_py/office/excel/xlsxwriter/xlworkbook.cp36-win32.pyd
haoqiren_py/office/word/pydocx/wdconstant.cp36-win32.pyd
haoqiren_py/office/word/pydocx/wddocument.cp36-win32.pyd
haoqiren_py/office/word/pydocx/wdheaderfooter.cp36-win32.pyd
haoqiren_py/office/word/pydocx/wdparagraph.cp36-win32.pyd
haoqiren_py/office/word/pydocx/wdrange.cp36-win32.pyd
haoqiren_py/office/word/pydocx/wdsection.cp36-win32.pyd
haoqiren_py/office/word/pydocx/wdtable.cp36-win32.pyd
haoqiren_py/ui/tkinter/tkform.cp36-win32.pyd
haoqiren_py/ui/tkinter/tkhelper.cp36-win32.pyd
haoqiren_py/ui/tkinter/tklayouthelper.cp36-win32.pyd
haoqiren_py/ui/wxpy/wxform.cp36-win32.pyd
haoqiren_py_ext-0.0.8.dist-info/METADATA
haoqiren_py_ext-0.0.8.dist-info/WHEEL
haoqiren_py_ext-0.0.8.dist-info/top_level.txt
haoqiren_py_ext-0.0.8.dist-info/RECORD
